{
    "vertical_barcodes_coords" :{
        "1 Standard Spine": [299, 582], "2 Standard A/R": [299, 599], "5": [299, 637],
        "G": [193, 579], "H": [272, 579], "C": [325, 579], "D": [404, 579],
        "V": [404, 607], "U": [325, 607], "I": [272, 607], "T": [193, 607],
        "E": [193, 637], "F": [272, 637], "A": [325, 637], "B": [404, 637],
        "L": [58, 447], "M": [156, 447], "X": [156, 475], "W": [58, 475],
        "J": [58, 503], "K": [156, 503], "3": [252, 511],
        "P": [447, 447], "Q": [540, 447], "Z": [540, 475], "Y": [447, 475],
        "N": [447, 503], "O": [540, 503], "4": [347, 512]
    },

    "vertical_spine_coords": {
        "1 Standard Spine": [299, 582], "2 Standard A/R": [299, 599], "5": [299, 645],
        "G": [193, 579], "H": [272, 579], "C": [325, 579], "D": [404, 579],
        "V": [404, 612], "U": [325, 612], "I": [272, 612], "T": [193, 612],
        "E": [193, 646], "F": [272, 646], "A": [325, 646], "B": [404, 646],
        "L": [58, 447], "M": [156, 447], "X": [156, 480], "W": [58, 480],
        "J": [58, 512], "K": [156, 512], "3": [252, 520],
        "P": [447, 447], "Q": [540, 447], "Z": [540, 480], "Y": [447, 480],
        "N": [447, 512], "O": [540, 512], "4": [347, 521]
    },

    "horizontal_barcodes_coords": {
        "1 Standard Spine": [289, 582], "2 Standard A/R": [289, 597], "5": [289, 657],
        "G": [194, 579], "H": [252, 579], "C": [325, 579], "D": [383, 579],
        "V": [383, 617], "U": [325, 617], "I": [252, 617], "T": [194, 617],
        "E": [194, 657], "F": [252, 657], "A": [325, 657], "B": [383, 657],
        "L": [58, 447], "M": [136, 447], "X": [136, 483], "W": [58, 483],
        "J": [58, 523], "K": [136, 523], "3": [234, 531],
        "P": [447, 447], "Q": [520, 447], "Z": [520, 483], "Y": [447, 483],
        "N": [447, 523], "O": [520, 523], "4": [349, 532]
    },

    "horizontal_spine_coords": {
        "1 Standard Spine": [293, 582], "2 Standard A/R": [293, 597], "5": [293, 657],
        "G": [194, 579], "H": [261, 579], "C": [325, 579], "D": [392, 579],
        "V": [392, 617], "U": [325, 617], "I": [261, 617], "T": [194, 617],
        "E": [194, 657], "F": [261, 657], "A": [325, 657], "B": [392, 657],
        "L": [58, 447], "M": [145, 447], "X": [145, 483], "W": [58, 483],
        "J": [58, 523], "K": [145, 523], "3": [241, 531],
        "P": [447, 447], "Q": [529, 447], "Z": [529, 483], "Y": [447, 483],
        "N": [447, 523], "O": [529, 523], "4": [349, 532]
    },

    "large_ar_coords": {
        "1 Standard Spine": [293.5, 582], "2 Standard A/R": [293.5, 597], "5": [293.5, 645],
        "G": [193, 579], "H": [262, 579], "C": [325, 579], "D": [394, 579],
        "V": [394, 612], "U": [325, 612], "I": [262, 612], "T": [193, 612],
        "E": [193, 646], "F": [262, 646], "A": [325, 646], "B": [394, 646],
        "L": [57, 447], "M": [146, 447], "X": [146, 480], "W": [57, 480],
        "J": [57, 514], "K": [146, 514], "3": [242, 522],
        "P": [446, 447], "Q": [530, 447], "Z": [530, 480], "Y": [446, 480],
        "N": [446, 514], "O": [530, 514], "4": [347, 522]
    },

    "horizontal_property_coords": {
        "1 Standard Spine": [286, 582], "2 Standard A/R": [286, 597], "5": [286, 657],
        "G": [194, 579], "H": [248, 579], "C": [325, 579], "D": [379, 579],
        "V": [379, 617], "U": [325, 617], "I": [248, 617], "T": [194, 617],
        "E": [194, 657], "F": [248, 657], "A": [325, 657], "B": [379, 657],
        "L": [58, 447], "M": [131, 447], "X": [131, 483], "W": [58, 483],
        "J": [58, 523], "K": [131, 523], "3": [228, 531],
        "P": [447, 447], "Q": [515, 447], "Z": [515, 483], "Y": [447, 483],
        "N": [447, 523], "O": [515, 523], "4": [346, 532]
    },

    "vertical_property_coords": {
        "1 Standard Spine": [299, 582], "2 Standard A/R": [299, 599], "5": [299, 632],
        "G": [193, 579], "H": [272, 579], "C": [325, 579], "D": [404, 579],
        "V": [404, 606], "U": [325, 606], "I": [272, 606], "T": [193, 606],
        "E": [193, 632], "F": [272, 632], "A": [325, 632], "B": [404, 632],
        "L": [58, 447], "M": [156, 447], "X": [156, 473], "W": [58, 473],
        "J": [58, 499], "K": [156, 499], "3": [252, 507],
        "P": [447, 447], "Q": [540, 447], "Z": [540, 473], "Y": [447, 473],
        "N": [447, 499], "O": [540, 499], "4": [347, 509]
    }
}